odoo/addons/mail_force_return_path/__init__.py
odoo/addons/mail_force_return_path/__manifest__.py
odoo/addons/mail_force_return_path/models/__init__.py
odoo/addons/mail_force_return_path/models/mail_mail.py
odoo12_addon_mail_force_return_path-12.0.1.0.1.dist-info/METADATA
odoo12_addon_mail_force_return_path-12.0.1.0.1.dist-info/WHEEL
odoo12_addon_mail_force_return_path-12.0.1.0.1.dist-info/top_level.txt
odoo12_addon_mail_force_return_path-12.0.1.0.1.dist-info/RECORD
